<PAMDataset>
  <PAMRasterBand band="1">
    <Description>1984</Description>
    <Histograms>
      <HistItem>
        <HistMin>-0.4993016759776536</HistMin>
        <HistMax>715.4993016759777</HistMax>
        <BucketCount>716</BucketCount>
        <IncludeOutOfRange>0</IncludeOutOfRange>
        <Approximate>0</Approximate>
        <HistCounts>59|14|0|0|0|2|0|0|3|8|14|0|0|0|0|0|5|0|3|15|10|2|2|0|2|2|0|13|28|10|5|4|3|6|6|7|5|15|17|13|16|4|4|5|8|18|19|13|11|17|11|9|6|17|22|6|21|19|28|18|20|15|8|12|12|15|22|23|17|19|35|18|23|17|29|13|23|22|25|18|20|24|35|17|48|21|37|52|22|40|45|31|35|24|55|28|39|36|37|31|37|55|8|67|16|56|44|41|50|49|55|32|40|56|30|57|24|72|29|57|42|41|59|27|93|20|77|23|66|43|36|67|57|73|51|34|29|72|54|69|69|55|50|80|54|70|35|74|75|29|65|95|8|88|75|11|95|71|28|69|64|46|81|68|52|74|62|56|72|78|68|94|57|85|89|40|96|77|41|101|35|132|56|74|67|81|115|93|63|67|88|79|108|75|99|98|71|71|120|74|52|55|133|97|30|24|101|211|7|1|22|307|18|5|40|202|110|25|75|140|129|77|63|79|126|88|105|131|133|81|73|90|123|137|97|96|77|138|96|75|140|22|185|97|140|101|126|140|89|132|126|92|100|150|71|101|176|23|227|108|3|317|28|43|233|66|127|180|121|111|154|108|167|111|118|128|148|83|163|71|220|32|226|14|248|35|222|85|193|109|137|109|180|101|170|155|81|207|74|179|162|146|138|134|172|96|149|162|130|178|143|103|126|151|172|159|206|139|159|144|157|184|234|168|122|107|66|139|210|283|254|110|45|22|55|116|292|642|175|35|2|2|3|6|82|1244|66|3|0|3|14|72|359|382|283|156|82|71|56|98|241|249|245|193|117|122|127|146|190|211|185|155|193|166|149|147|245|171|161|236|165|129|225|117|202|257|95|261|149|218|153|213|220|208|211|158|170|208|137|233|192|199|270|125|229|162|145|394|27|372|130|54|431|76|179|266|196|197|156|301|107|236|281|121|203|201|214|149|163|245|273|97|158|409|169|10|52|748|14|7|301|430|47|61|286|288|167|183|180|233|197|196|260|93|200|248|214|300|165|257|170|120|346|19|382|167|111|331|127|180|227|146|245|279|146|323|73|308|123|228|296|137|190|215|120|280|193|255|163|94|264|278|260|273|89|69|114|215|433|369|177|37|18|6|88|850|451|13|3|0|4|53|571|703|105|15|22|26|196|289|320|316|112|120|78|199|223|215|232|166|68|219|192|123|135|237|87|300|124|170|167|109|211|58|339|84|119|221|36|261|58|166|154|184|122|162|138|101|215|161|13|107|315|3|55|298|64|23|143|141|129|107|96|137|129|53|180|41|155|5|211|50|104|54|75|79|50|159|22|121|70|80|22|74|106|121|77|17|7|24|149|153|41|6|0|0|44|298|0|1|5|5|62|112|117|5|7|36|46|57|51|61|18|17|22|31|43|42|27|14|41|11|39|18|38|28|22|12|29|13|26|27|0|3|47|2|15|21|8|18|13|7|30|3|5|7|7|11|11|5|3|2|5|8|8|12|7|0|2|23|6|1|0|0|5|5|0|0|6|2|0|1|2|0|0|2|2|0|0|0|1|0|0|1|0|0|2|0|0|0|0|2|0|0|2|0|0|0|3|0|0|0|2|0|0|2</HistCounts>
      </HistItem>
    </Histograms>
    <Metadata>
      <MDI key="STATISTICS_MAXIMUM">715</MDI>
      <MDI key="STATISTICS_MEAN">386.17541683891</MDI>
      <MDI key="STATISTICS_MINIMUM">0</MDI>
      <MDI key="STATISTICS_STDDEV">133.97271141724</MDI>
      <MDI key="STATISTICS_VALID_PERCENT">100</MDI>
    </Metadata>
  </PAMRasterBand>
  <PAMRasterBand band="2">
    <Description>1985</Description>
    <Histograms>
      <HistItem>
        <HistMin>-0.4992721979621543</HistMin>
        <HistMax>686.4992721979621</HistMax>
        <BucketCount>687</BucketCount>
        <IncludeOutOfRange>0</IncludeOutOfRange>
        <Approximate>0</Approximate>
        <HistCounts>86|3|1|0|0|0|0|6|16|21|3|0|0|0|0|0|3|12|7|21|6|3|1|1|4|11|12|12|12|13|9|6|8|3|6|5|10|7|18|21|26|8|7|12|11|11|13|22|18|16|28|8|12|27|35|15|11|30|24|22|24|21|30|23|25|27|21|19|26|25|41|26|21|38|27|39|25|17|44|38|23|32|32|45|38|41|27|25|41|39|48|36|21|46|36|33|55|37|48|50|26|58|16|66|37|52|55|53|58|38|70|43|59|46|39|45|72|48|60|61|52|49|71|35|110|22|99|34|63|59|44|41|53|68|63|87|50|54|77|85|69|68|73|73|55|57|79|74|39|88|87|48|86|100|66|54|87|71|69|93|68|64|99|60|74|78|69|89|93|73|69|76|87|84|81|67|62|118|49|101|38|144|56|109|93|79|78|105|103|81|92|89|91|92|84|88|111|110|112|94|110|130|130|68|81|165|130|72|16|156|114|178|13|84|130|215|81|69|141|159|162|104|97|130|156|133|104|106|133|173|141|121|103|157|147|126|111|174|162|71|170|105|174|120|161|145|112|167|110|178|140|137|152|107|170|117|115|178|169|153|114|199|143|115|228|129|164|214|160|181|191|144|142|195|164|150|159|161|188|166|187|192|201|113|252|137|212|171|177|181|142|210|201|168|153|239|134|264|103|225|105|239|182|160|208|182|151|228|113|187|240|185|185|229|194|139|165|172|220|232|228|196|184|146|142|180|255|308|281|201|126|67|64|98|229|413|518|243|81|31|9|2|14|327|558|763|73|1|3|22|40|138|334|497|514|215|143|105|91|118|188|255|307|296|228|191|171|173|197|220|225|252|182|181|210|158|209|262|194|226|214|254|222|193|165|252|171|243|197|305|211|252|216|206|254|191|204|289|203|248|173|187|208|275|146|203|319|96|205|384|149|170|356|155|137|266|155|228|238|143|238|186|253|162|228|237|252|182|232|197|122|219|389|177|86|149|487|183|62|84|308|443|92|107|212|291|230|133|159|219|242|209|137|247|165|229|249|188|216|150|131|379|110|136|331|174|116|316|135|208|311|128|207|185|93|254|121|281|146|253|130|184|93|195|171|190|107|204|213|265|164|177|124|60|88|111|289|337|287|108|47|24|14|56|439|477|144|65|10|2|8|81|288|509|175|5|6|42|56|125|236|229|174|128|59|49|71|140|94|145|117|80|137|88|120|79|117|79|105|83|64|142|42|95|107|47|98|61|68|81|73|56|92|31|99|56|39|106|86|31|38|123|37|27|34|100|28|23|40|93|29|17|41|55|28|42|22|43|30|30|30|29|60|25|22|59|25|32|39|38|13|21|31|44|33|19|8|2|10|28|43|14|8|3|2|6|60|20|9|2|1|2|13|36|18|5|2|4|2|16|24|11|4|1|6|5|5|7|12|6|2|6|10|4|5|0|7|2|6|1|1|1|1|5|0|1|0|1|1|4|1|0|2|1|1|0|3|1|2|0|0|0|2|0|0|0|0|0|0|0|0|0|0|0|1|0|0|0|0|0|0|0|0|0|0|0|2</HistCounts>
      </HistItem>
    </Histograms>
    <Metadata>
      <MDI key="STATISTICS_MAXIMUM">686</MDI>
      <MDI key="STATISTICS_MEAN">352.72966790685</MDI>
      <MDI key="STATISTICS_MINIMUM">0</MDI>
      <MDI key="STATISTICS_STDDEV">123.68948977363</MDI>
      <MDI key="STATISTICS_VALID_PERCENT">100</MDI>
    </Metadata>
  </PAMRasterBand>
  <PAMRasterBand band="3">
    <Description>1986</Description>
    <Histograms>
      <HistItem>
        <HistMin>-0.4992236024844721</HistMin>
        <HistMax>643.4992236024844</HistMax>
        <BucketCount>644</BucketCount>
        <IncludeOutOfRange>0</IncludeOutOfRange>
        <Approximate>0</Approximate>
        <HistCounts>233|10|3|3|1|0|0|4|18|37|26|0|0|0|1|4|3|36|50|47|19|9|7|5|3|13|28|46|20|32|25|13|14|24|20|33|28|36|44|25|25|16|22|35|38|21|53|34|35|51|40|31|54|29|30|44|47|58|47|31|45|49|41|37|43|62|56|51|46|41|54|65|56|69|50|52|49|62|61|53|60|50|80|61|62|66|54|70|39|61|69|56|62|84|56|63|89|69|61|76|50|105|46|79|51|82|86|60|95|81|71|78|63|96|75|88|80|79|81|104|61|93|83|90|100|103|103|83|98|83|90|73|112|72|103|94|69|134|97|100|103|100|100|87|94|98|89|110|97|114|165|58|96|176|80|76|153|76|95|129|133|111|122|118|109|144|122|160|148|101|112|114|133|137|133|168|129|127|119|146|120|129|145|160|79|135|129|154|163|123|126|179|157|141|133|137|145|157|151|114|170|218|143|103|122|203|292|80|18|105|281|413|22|16|133|314|232|126|121|201|197|172|122|125|206|216|129|169|151|185|187|154|198|199|172|190|202|178|186|148|246|127|224|161|202|169|186|201|235|234|246|211|180|188|224|233|166|198|284|83|169|307|137|158|335|177|184|264|218|241|211|179|195|295|218|173|192|240|185|251|173|190|246|168|252|220|291|179|222|282|220|219|242|260|212|271|185|253|178|233|174|277|223|217|298|192|248|217|210|278|275|225|191|224|229|265|235|242|280|233|280|170|192|203|255|334|283|311|236|164|98|133|159|203|352|559|556|214|48|9|8|13|22|50|666|1094|415|28|1|2|4|47|165|285|576|452|339|270|120|92|127|183|208|254|294|282|294|260|204|219|222|181|212|249|153|210|220|261|210|288|226|212|219|226|171|192|152|224|228|218|236|183|293|124|242|179|209|232|194|226|217|215|234|213|160|195|258|124|156|325|116|144|288|180|128|202|196|130|163|203|132|187|173|174|237|130|189|232|192|109|90|233|301|83|24|124|318|244|8|11|187|290|144|38|122|211|217|100|99|144|154|148|135|131|126|134|113|108|135|80|62|229|84|87|154|74|58|141|74|93|145|111|92|83|73|66|60|87|102|119|123|103|73|73|50|62|79|87|84|78|56|54|38|30|53|89|116|124|50|5|7|6|6|49|183|175|36|6|1|0|0|13|87|133|71|34|11|1|5|9|47|49|57|44|47|23|11|15|30|21|32|28|29|18|19|24|36|19|20|24|4|47|7|18|20|15|22|11|1|25|13|8|19|22|20|5|13|24|10|2|6|28|21|3|3|14|7|2|4|7|10|9|3|7|5|4|0|12|7|3|8|6|2|5|3|5|1|5|1|2|0|1|3|5|0|1|2|0|0|3|4|1|1|0|2|0|1|7|2|0|0|0|0|2|0|1|0|0|0|0|6|0|0|0|0|1|0|0|1|0|0|1|1|2|0|0|0|0|0|0|0|0|0|1</HistCounts>
      </HistItem>
    </Histograms>
    <Metadata>
      <MDI key="STATISTICS_MAXIMUM">643</MDI>
      <MDI key="STATISTICS_MEAN">299.59113958936</MDI>
      <MDI key="STATISTICS_MINIMUM">0</MDI>
      <MDI key="STATISTICS_STDDEV">115.71174536644</MDI>
      <MDI key="STATISTICS_VALID_PERCENT">100</MDI>
    </Metadata>
  </PAMRasterBand>
  <PAMRasterBand band="4">
    <Description>1987</Description>
  </PAMRasterBand>
  <PAMRasterBand band="5">
    <Description>1988</Description>
  </PAMRasterBand>
  <PAMRasterBand band="6">
    <Description>1989</Description>
  </PAMRasterBand>
  <PAMRasterBand band="7">
    <Description>1990</Description>
  </PAMRasterBand>
  <PAMRasterBand band="8">
    <Description>1991</Description>
  </PAMRasterBand>
  <PAMRasterBand band="9">
    <Description>1992</Description>
  </PAMRasterBand>
  <PAMRasterBand band="10">
    <Description>1993</Description>
  </PAMRasterBand>
  <PAMRasterBand band="11">
    <Description>1994</Description>
  </PAMRasterBand>
  <PAMRasterBand band="12">
    <Description>1995</Description>
  </PAMRasterBand>
  <PAMRasterBand band="13">
    <Description>1996</Description>
  </PAMRasterBand>
  <PAMRasterBand band="14">
    <Description>1997</Description>
  </PAMRasterBand>
  <PAMRasterBand band="15">
    <Description>1998</Description>
  </PAMRasterBand>
  <PAMRasterBand band="16">
    <Description>1999</Description>
  </PAMRasterBand>
  <PAMRasterBand band="17">
    <Description>2000</Description>
  </PAMRasterBand>
  <PAMRasterBand band="18">
    <Description>2001</Description>
  </PAMRasterBand>
  <PAMRasterBand band="19">
    <Description>2002</Description>
  </PAMRasterBand>
  <PAMRasterBand band="20">
    <Description>2003</Description>
  </PAMRasterBand>
  <PAMRasterBand band="21">
    <Description>2004</Description>
  </PAMRasterBand>
  <PAMRasterBand band="22">
    <Description>2005</Description>
  </PAMRasterBand>
  <PAMRasterBand band="23">
    <Description>2006</Description>
  </PAMRasterBand>
  <PAMRasterBand band="24">
    <Description>2007</Description>
  </PAMRasterBand>
  <PAMRasterBand band="25">
    <Description>2008</Description>
  </PAMRasterBand>
  <PAMRasterBand band="26">
    <Description>2009</Description>
  </PAMRasterBand>
  <PAMRasterBand band="27">
    <Description>2010</Description>
  </PAMRasterBand>
  <PAMRasterBand band="28">
    <Description>2011</Description>
  </PAMRasterBand>
  <PAMRasterBand band="29">
    <Description>2012</Description>
  </PAMRasterBand>
  <PAMRasterBand band="30">
    <Description>2013</Description>
  </PAMRasterBand>
  <PAMRasterBand band="31">
    <Description>2014</Description>
  </PAMRasterBand>
  <PAMRasterBand band="32">
    <Description>2015</Description>
  </PAMRasterBand>
  <PAMRasterBand band="33">
    <Description>2016</Description>
  </PAMRasterBand>
  <PAMRasterBand band="34">
    <Description>2017</Description>
  </PAMRasterBand>
  <PAMRasterBand band="35">
    <Description>2018</Description>
  </PAMRasterBand>
  <PAMRasterBand band="36">
    <Description>2019</Description>
  </PAMRasterBand>
  <PAMRasterBand band="37">
    <Description>2020</Description>
  </PAMRasterBand>
  <PAMRasterBand band="38">
    <Description>2021</Description>
  </PAMRasterBand>
</PAMDataset>
